commentary/__init__.py
commentary/commentary.py
commentary/commentary_filter.py
commentary/version.py
commentary/data/commentary_conf.json
commentary-0.3.1.data/scripts/commentary
commentary-0.3.1.data/scripts/commentary-filter
commentary-0.3.1.dist-info/LICENSE
commentary-0.3.1.dist-info/METADATA
commentary-0.3.1.dist-info/WHEEL
commentary-0.3.1.dist-info/top_level.txt
commentary-0.3.1.dist-info/RECORD
