Metadata-Version: 2.1
Name: commentary
Version: 0.3.1
Summary: comment-preserving docx <-- --> markdown converter
Home-page: https://github.com/hdb/commentary
Author: Hudson Bailey
Author-email: hudsondiggsbailey@gmail.com
License: MIT
Platform: UNKNOWN
Classifier: Programming Language :: Python :: 3
Classifier: Operating System :: OS Independent
License-File: LICENSE
Requires-Dist: pypandoc (>=1.4)
Requires-Dist: pandocfilters (==1.5.0)
